{"node":{"56017a89fc3eb7521b02c25a9f4a2e0513ec4799":{"workers":{"app/[locale]/account/page":"32341","app/[locale]/dashboard/page":"32341"},"layer":{"app/[locale]/account/page":"rsc","app/[locale]/dashboard/page":"rsc"}},"7235de739053e412e4a92e507096e1b22eab8ac2":{"workers":{"app/[locale]/account/page":"32341","app/[locale]/dashboard/page":"32341"},"layer":{"app/[locale]/account/page":"rsc","app/[locale]/dashboard/page":"rsc"}}},"edge":{},"encryptionKey":"m8+EEabI6cz1Y1+qhdXeyYVd3J0CrX/eMr/KpMpFurU="}